pytraceability/__init__.py
pytraceability/ast_processing.py
pytraceability/cli.py
pytraceability/collector.py
pytraceability/common.py
pytraceability/config.py
pytraceability/custom.py
pytraceability/data_definition.py
pytraceability/exceptions.py
pytraceability/history.py
pytraceability/html.py
pytraceability/import_processing.py
pytraceability/logging.py
pytraceability-0.0.1a1.dist-info/LICENSE
pytraceability-0.0.1a1.dist-info/METADATA
pytraceability-0.0.1a1.dist-info/WHEEL
pytraceability-0.0.1a1.dist-info/entry_points.txt
pytraceability-0.0.1a1.dist-info/RECORD
