Metadata-Version: 2.1
Name: pytraceability
Version: 0.0.1a1
Summary: A python library for linking code to requirements
License: MIT
Author: Max Shepherd
Requires-Python: >=3.8,<4.0
Classifier: License :: OSI Approved :: MIT License
Classifier: Programming Language :: Python :: 3
Classifier: Programming Language :: Python :: 3.8
Classifier: Programming Language :: Python :: 3.9
Classifier: Programming Language :: Python :: 3.10
Classifier: Programming Language :: Python :: 3.11
Classifier: Programming Language :: Python :: 3.12
Classifier: Programming Language :: Python :: 3.13
Requires-Dist: click (>=8.0.0)
Requires-Dist: colorama (>=0.4.6,<0.5.0)
Requires-Dist: eval-type-backport (>=0.2.2,<0.3.0)
Requires-Dist: jinja2 (>=3.1.6,<4.0.0)
Requires-Dist: pydantic (>=2.10.6,<3.0.0)
Requires-Dist: pydriller (>=2.7,<3.0)
Requires-Dist: tomli (>=2.2.1,<3.0.0)
